structjour/__init__.py
structjour/dailysumforms.py
structjour/definetrades.py
structjour/dfutil.py
structjour/journalfiles.py
structjour/layoutsheet.py
structjour/readme.md
structjour/thetradeobject.py
structjour/time.py
structjour/tradestyle.py
structjour/version.py
structjour/xlimage.py
structjour/colz/__init__.py
structjour/colz/finreqcol.py
structjour/discipline/__init__.py
structjour/discipline/disciplined.py
structjour/discipline/getfiles.py
structjour/images/ZSLogo.png
structjour/images/ZeroSubstanceCreation.png
structjour/images/ZeroSubstanceCreation_220.png
structjour/images/ZeroSubstanceCreation_500x334.png
structjour/inspiration/__init__.py
structjour/inspiration/inspire.py
structjour/inspiration/load.py
structjour/migrations/_0002_structjour_statement_ibstatementdb.py
structjour/migrations/_0003_model_trade_sum_dataonly.py
structjour/migrations/__init__.py
structjour/migrations/check_migration.py
structjour/models/__init__.py
structjour/models/meta.py
structjour/models/strategymodels.py
structjour/models/trademodels.py
structjour/statements/__init__.py
structjour/statements/dailynotes.py
structjour/statements/dasstatement.py
structjour/statements/dbdoctor.py
structjour/statements/findfiles.py
structjour/statements/ibstatement.py
structjour/statements/ibstatementdb.py
structjour/statements/ibstatements_notused.py
structjour/statements/statement.py
structjour/stock/__init__.py
structjour/stock/apichooser.py
structjour/stock/graphstuff.py
structjour/stock/myFinhub.py
structjour/stock/myWTD.py
structjour/stock/myalphavantage.py
structjour/stock/mybarchart.py
structjour/stock/myib.py
structjour/stock/myiex.py
structjour/stock/utilities.py
structjour/strategy/__init__.py
structjour/strategy/load.py
structjour/strategy/strat.py
structjour/strategy/strategies.py
structjour/utilities/__init__.py
structjour/utilities/backup.py
structjour/utilities/rtg.py
structjour/utilities/synchronizesavedstuff.py
structjour/utilities/util.py
structjour/view/__init__.py
structjour-0.9.93a0.dist-info/LICENSE
structjour-0.9.93a0.dist-info/METADATA
structjour-0.9.93a0.dist-info/WHEEL
structjour-0.9.93a0.dist-info/entry_points.txt
structjour-0.9.93a0.dist-info/top_level.txt
structjour-0.9.93a0.dist-info/RECORD
