Metadata-Version: 2.1
Name: structjour
Version: 0.9.93a0
Summary: A structured daily journal for day traders.
Home-page: https://github.com/MikePia/structjour
Author: Mike Petersen
Author-email: pentsok@zerosubstance.org
License: GPL
Keywords: DayTrading journal
Platform: UNKNOWN
Classifier: Development Status :: 3 - Alpha
Classifier: Intended Audience :: Other Audience
Classifier: Programming Language :: Python :: 3
Classifier: License :: OSI Approved :: GNU General Public License v3 (GPLv3)
Classifier: Operating System :: Microsoft :: Windows
Requires-Python: >=3.6
Requires-Dist: requests
Requires-Dist: Pillow
Requires-Dist: numpy (>=1.16.0)
Requires-Dist: pandas (>=0.24.0)
Requires-Dist: matplotlib (>=3.1.0sqlalchemy>=1.3.16seaborn>=0.9.0)
Requires-Dist: PyQtWebEngine (>=5.12.1)
Requires-Dist: PyQt5 (>=5.13.0)
Requires-Dist: pyqt5-sip
Requires-Dist: openpyxl (>=2.5.14)
Requires-Dist: beautifulsoup4 (>=4.7.1)
Requires-Dist: mpl-finance (==0.10.0)
